{
  "title" : "Juris-Doctor-Non-Thesis-Curriculum",
  "program_name": "Juris Doctor",
  "track": "Non-Thesis",
  "institution": "Saint Louis University",
  "location": "Baguio City, Philippines",
  "compliance": {
    "agency": "Legal Education Board",
    "certification_reference": "LEBMO No. 24, Series of 2021",
    "legal_basis": "Republic Act No. 7662 (Legal Education Reform Act of 1993)",
    "approved_year": "2022–2023"
  },
  "program_details": {
    "schedule": "4 years",
    "academic_track": "None",
    "total_units": 137,
    "enhanced_units": 2
  },
  "courses": [
    { "year": 1, "term": 1, "subject": "Philosophy of Law", "units": 2, "prerequisite": "None" },
    { "year": 1, "term": 1, "subject": "Constitutional Law I", "units": 3, "prerequisite": "None" },
    { "year": 1, "term": 1, "subject": "Criminal Law I", "units": 3, "prerequisite": "None" },
    { "year": 1, "term": 1, "subject": "Obligations and Contracts", "units": 4, "prerequisite": "None" },
    { "year": 1, "term": 1, "subject": "Basic Legal and Judicial Ethics", "units": 3, "prerequisite": "None" },
    { "year": 1, "term": 1, "subject": "Statutory Construction", "units": 2, "prerequisite": "None" },

    { "year": 1, "term": 2, "subject": "Criminal Law II", "units": 4, "prerequisite": "Criminal Law I" },
    { "year": 1, "term": 2, "subject": "Legal Research and Writing", "units": 3, "prerequisite": "None" },
    { "year": 1, "term": 2, "subject": "Criminal Procedure", "units": 3, "prerequisite": "None" },

    { "year": 2, "term": 1, "subject": "Public International Law", "units": 2, "prerequisite": "None" },
    { "year": 2, "term": 1, "subject": "Persons and Family Law", "units": 3, "prerequisite": "None" },
    { "year": 2, "term": 1, "subject": "Civil Procedure I", "units": 3, "prerequisite": "None" },
    { "year": 2, "term": 1, "subject": "Agency, Trust and Partnership Law", "units": 3, "prerequisite": "Obligations and Contracts" },
    { "year": 2, "term": 1, "subject": "Corporation and Basic Securities Law", "units": 3, "prerequisite": "Obligations and Contracts" },
    { "year": 2, "term": 1, "subject": "Labor Law and Social Legislation", "units": 3, "prerequisite": "None" },
    { "year": 2, "term": 1, "subject": "Constitutional Law II", "units": 3, "prerequisite": "Constitutional Law I" },
    { "year": 2, "term": 1, "subject": "Clinical Legal Education I", "units": 1, "prerequisite": "None" },

    { "year": 2, "term": 2, "subject": "Civil Procedure II", "units": 2, "prerequisite": "Civil Procedure I" },
    { "year": 2, "term": 2, "subject": "Basic Succession Law", "units": 2, "prerequisite": "Persons and Family Law" },
    { "year": 2, "term": 2, "subject": "Property and Land Law", "units": 3, "prerequisite": "None" },
    { "year": 2, "term": 2, "subject": "Commercial Laws", "units": 3, "prerequisite": "Obligations and Contracts, Corporation and Basic Securities Law" },
    { "year": 2, "term": 2, "subject": "Basic Taxation Law", "units": 3, "prerequisite": "Constitutional Law II" },
    { "year": 2, "term": 2, "subject": "Administrative Law and Law on Public Officers", "units": 3, "prerequisite": "Constitutional Law II" },
    { "year": 2, "term": 2, "subject": "Environmental and Natural Resources Law", "units": 3, "prerequisite": "None" },

    { "year": 3, "term": 1, "subject": "Evidence", "units": 3, "prerequisite": "Criminal Procedure, Civil Procedure I & II" },
    { "year": 3, "term": 1, "subject": "Torts and Damages", "units": 2, "prerequisite": "Obligations and Contracts" },
    { "year": 3, "term": 1, "subject": "Private International Law", "units": 2, "prerequisite": "Various prerequisites" },
    { "year": 3, "term": 1, "subject": "Special Rules and Proceedings", "units": 2, "prerequisite": "Criminal Procedure, Civil Procedure" },
    { "year": 3, "term": 1, "subject": "Legal Forms", "units": 2, "prerequisite": "None" },
    { "year": 3, "term": 1, "subject": "Laws on Local Government", "units": 2, "prerequisite": "None" },

    { "year": 3, "term": 2, "subject": "Medical Jurisprudence", "units": 1, "prerequisite": "None" },
    { "year": 3, "term": 2, "subject": "Gender Sensitivity and Laws on Women and Children’s Rights", "units": 2, "prerequisite": "None" },
    { "year": 3, "term": 2, "subject": "Electives", "units": "As applicable", "prerequisite": "As applicable" },

    { "year": 4, "term": 1, "subject": "Civil Law Review and Integration", "units": 4, "prerequisite": "All major Civil Law subjects" },
    { "year": 4, "term": 1, "subject": "Political and International Law Review and Integration", "units": 4, "prerequisite": "All major Political/International Law subjects" },
    { "year": 4, "term": 1, "subject": "Criminal Law Review and Integration", "units": 3, "prerequisite": "Criminal Law I & II" },
    { "year": 4, "term": 1, "subject": "Labor Law Review and Integration", "units": 3, "prerequisite": "Labor Law and Social Legislation" },
    { "year": 4, "term": 1, "subject": "Clinical Legal Education II", "units": 5, "prerequisite": "Clinical Legal Education I" },

    { "year": 4, "term": 2, "subject": "Remedial Law Review and Integration", "units": 4, "prerequisite": "Criminal/Civil Procedure, Evidence, Special Proceedings" },
    { "year": 4, "term": 2, "subject": "Commercial Law Review and Integration", "units": 4, "prerequisite": "All major Commercial Law subjects" },
    { "year": 4, "term": 2, "subject": "Taxation Law Review and Integration", "units": 2, "prerequisite": "Taxation Law" },
    { "year": 4, "term": 2, "subject": "Legal and Judicial Ethics and Practice Exercises", "units": 2, "prerequisite": "Basic Legal and Judicial Ethics" },
    { "year": 4, "term": 2, "subject": "Legal Forms", "units": 2, "prerequisite": "None" }
  ],
  "contact": {
    "agency": "Legal Education Board",
    "address": "G/F Red Cross Building, Carlos P. Garcia Avenue, Diliman, Quezon City 1104",
    "email": "contact@leb.gov.ph",
    "website": "https://leb.gov.ph",
    "phone": "(02) 8929-6929"
  }
}
